Metadata-Version: 2.4
Name: llm-fragments-dir
Version: 0.1
Summary: Load files from a local directory as fragments
Author: R. Keelan
License-Expression: Apache-2.0
Project-URL: Homepage, https://github.com/rkeelan/llm-fragments-dir
Project-URL: Changelog, https://github.com/rkeelan/llm-fragments-dir/releases
Project-URL: Issues, https://github.com/rkeelan/llm-fragments-dir/issues
Project-URL: CI, https://github.com/rkeelan/llm-fragments-dir/actions
Requires-Python: >=3.9
License-File: LICENSE
Requires-Dist: llm
Provides-Extra: test
Requires-Dist: pytest; extra == "test"
Dynamic: license-file
